{
  "tanks": {
    "0": {
      "fish": [
        {
          "id": 1781443567548,
          "name": "블루 시클라드",
          "latin": "blue",
          "desc": "",
          "dep": "",
          "tier": "md",
          "layer": "mid",
          "count": 5,
          "speed": 0.55,
          "imgW": 1440,
          "imgH": 900,
          "src": "https://raw.githubusercontent.com/norang1225/aquive/main/images/fish/tank0_1781443567548.png"
        }
      ],
      "bg": {
        "base": "https://raw.githubusercontent.com/norang1225/aquive/main/images/bg/tank0_base.png",
        "caustic": "https://raw.githubusercontent.com/norang1225/aquive/main/images/bg/tank0_caustic.png",
        "volume": "https://raw.githubusercontent.com/norang1225/aquive/main/images/bg/tank0_volume.png",
        "shimmer": "https://raw.githubusercontent.com/norang1225/aquive/main/images/bg/tank0_shimmer.png"
      }
    },
    "1": {
      "fish": [],
      "bg": {}
    },
    "2": {
      "fish": [],
      "bg": {}
    },
    "3": {
      "fish": [],
      "bg": {}
    },
    "4": {
      "fish": [],
      "bg": {}
    },
    "5": {
      "fish": [],
      "bg": {}
    },
    "6": {
      "fish": [],
      "bg": {}
    },
    "7": {
      "fish": [],
      "bg": {}
    },
    "8": {
      "fish": [],
      "bg": {}
    },
    "9": {
      "fish": [],
      "bg": {}
    },
    "10": {
      "fish": [],
      "bg": {}
    },
    "11": {
      "fish": [],
      "bg": {}
    },
    "12": {
      "fish": [],
      "bg": {}
    }
  }
}